Excel_Trans/Excel_translator.py
Excel_Trans/__init__.py
Excel_Trans/test.py
Excel_Trans/transliterate.py
Excel_Trans-1.22.1.dist-info/LICENSE
Excel_Trans-1.22.1.dist-info/METADATA
Excel_Trans-1.22.1.dist-info/WHEEL
Excel_Trans-1.22.1.dist-info/top_level.txt
Excel_Trans-1.22.1.dist-info/RECORD
