Metadata-Version: 2.1
Name: Excel-Trans
Version: 1.22.1
Summary: Excel Translate
Home-page: UNKNOWN
Author: Quvonchbek Bobojonov
Author-email: quvonchbek212006@gmail.com
License: UNKNOWN
Keywords: python,numpy,excel,Excel-Trans
Platform: UNKNOWN
Classifier: Development Status :: 1 - Planning
Classifier: Intended Audience :: Developers
Classifier: Programming Language :: Python :: 3
Classifier: Operating System :: Unix
Classifier: Operating System :: MacOS :: MacOS X
Classifier: Operating System :: Microsoft :: Windows
License-File: LICENSE
Requires-Dist: deep-translator (==1.9.0)
Requires-Dist: numpy (==1.23.4)
Requires-Dist: openpyxl (==3.0.10)
Requires-Dist: pandas (==1.5.1)
